redis_interval
