Metadata-Version: 1.1
Name: redis-interval
Version: 0.2.0
Summary: Extension of the python library for Redis with the Intervalsets extension of Redis
Home-page: https://github.com/globocom/redis-pyinterval
Author: Gustavo Pantuza
Author-email: gustavopantuza@gmail.com
License: UNKNOWN
Download-URL: https://github.com/globocom/redis-pyinterval/archive/0.2.0.tar.gz
Platform: UNKNOWN
